[
  {
    "id": 0,
    "offset": 277366,
    "data_size": 186,
    "slot_size": 190,
    "_term": [
      4358,
      4354,
      4355,
      5169
    ],
    "nom_orig": "Lucky[SP]cat[SP]statue",
    "texte_orig": "You[SP]have[SP]too[SP]many[SP]Incense[SP]sets,[SP]meow![SP]I[SP]can't\ngive[SP]you[SP]any[SP]more,[SP]meow!",
    "nom_fr": "Statue de chat",
    "texte_fr": "Trop de sets d'Encens, miaou ! Je\nne peux plus t'en donner, miaou !"
  },
  {
    "id": 1,
    "offset": 277556,
    "data_size": 284,
    "slot_size": 288,
    "_term": [
      4358,
      4354,
      4355,
      5169
    ],
    "nom_orig": "Eikichi",
    "texte_orig": "Can't[SP]we[SP]do[SP]something[SP]about[SP]the[SP]situation\nby[SP]spreading[SP]our[SP]own[SP]rumors?[SP]Like,[SP]the[SP]Earth\nwill[SP]be[SP]fine,[SP]or[SP]the[SP]In[SP]Lak'ech[SP]is[SP]a[SP]hoax.",
    "nom_fr": "Eikichi",
    "texte_fr": "Ne peut-on pas arranger ça en\nrépandant nos rumeurs ? Genre, la Terre\nira bien, ou In Lak'ech est un canular."
  },
  {
    "id": 2,
    "offset": 277844,
    "data_size": 268,
    "slot_size": 272,
    "_term": [
      4358,
      4354,
      4355,
      5169
    ],
    "nom_orig": "Eikichi",
    "texte_orig": "Sheesh,[SP]what[SP]a[SP]complete[SP]and[SP]utter[SP]coward...[1205][U+000A]\nC'mon,[SP]aren't[SP]you[SP]some[SP]ace[SP]detective[SP]who\nthrives[SP]in[SP]the[SP]shadow[SP]of[SP]the[SP]city?",
    "nom_fr": "Eikichi",
    "texte_fr": "Pfff, quel lâche absolu...[1205][U+000A]\nT'es pas censé être un as détective\nqui prospère dans l'ombre de la ville ?"
  },
  {
    "id": 3,
    "offset": 278116,
    "data_size": 206,
    "slot_size": 210,
    "_term": [
      4358,
      4354,
      4355,
      5169
    ],
    "nom_orig": "Ginko",
    "texte_orig": "Could[SP]the[SP]part[SP]about[SP]the[SP]Earth[SP]being[SP]annihilated\ncome[SP]true,[SP]too?[1205][U+000F][SP]Yeah,[SP]I'm[SP]sure[SP]it[SP]will...",
    "nom_fr": "Ginko",
    "texte_fr": "La destruction de la Terre\nva-t-elle aussi se réaliser ?[1205][U+000F]\nOuais, j'en suis sûre..."
  },
  {
    "id": 4,
    "offset": 278326,
    "data_size": 272,
    "slot_size": 276,
    "_term": [
      4358,
      4354,
      4355,
      5169
    ],
    "nom_orig": "Ginko",
    "texte_orig": "What're[SP]we[SP]gonna[SP]do?[1205][U+000F][SP]Everyone's[SP]gossiping[SP]about\nhow[SP]the[SP]world's[SP]gonna[SP]end[SP]down[SP]there,[SP]just\nbecause[SP]they[SP]think[SP]they're[SP]safe.",
    "nom_fr": "Ginko",
    "texte_fr": "Que va-t-on faire ?[1205][U+000F] Tous parlent de\nla fin du monde en bas, juste\nparce qu'ils se croient en sécurité."
  },
  {
    "id": 5,
    "offset": 278602,
    "data_size": 138,
    "slot_size": 142,
    "_term": [
      4358,
      4354,
      4355,
      5169
    ],
    "nom_orig": "Ginko",
    "texte_orig": "Hey,[SP]quit[SP]it,[SP]Eikichi![SP]You[SP]don't[SP]have[SP]to[SP]say\nit[SP]like[SP]that.",
    "nom_fr": "Ginko",
    "texte_fr": "Hé, arrête Eikichi ! Tu n'as pas\nà dire ça comme ça."
  },
  {
    "id": 6,
    "offset": 278744,
    "data_size": 272,
    "slot_size": 276,
    "_term": [
      4358,
      4354,
      4355,
      5169
    ],
    "nom_orig": "Maya",
    "texte_orig": "Yeah...[1205][U+000A][SP]At[SP]this[SP]rate,[SP]the[SP]people[SP]of[SP]Sumaru[SP]will\ndestroy[SP]the[SP]world...[1205][U+000F][SP]We[SP]have[SP]to[SP]do[SP]something\nbefore[SP]it[SP]gets[SP]to[SP]that[SP]stage.",
    "nom_fr": "Maya",
    "texte_fr": "Ouais...[1205][U+000A] À ce rythme, les gens de Sumaru\ndétruiront le monde...[1205][U+000F] Il faut agir\navant d'en arriver là."
  },
  {
    "id": 7,
    "offset": 279020,
    "data_size": 166,
    "slot_size": 170,
    "_term": [
      4358,
      4354,
      4355,
      5169
    ],
    "nom_orig": "Maya",
    "texte_orig": "Tell[SP]Tamaki-san[SP]not[SP]to[SP]worry[SP]so[SP]much[SP]about[SP]it,\n[1113]-kun.[1205][U+000F][SP]We[SP]can[SP]handle[SP]it.",
    "nom_fr": "Maya",
    "texte_fr": "Dis à Tamaki de ne pas s'en\nfaire, [1113]-kun.[1205][U+000F] On gère."
  },
  {
    "id": 8,
    "offset": 279190,
    "data_size": 206,
    "slot_size": 210,
    "_term": [
      4358,
      4354,
      4355,
      5169
    ],
    "nom_orig": "Jun",
    "texte_orig": "We've[SP]got[SP]no[SP]choice[SP]but[SP]to[SP]stop[SP]my[SP]father.[1205][U+000F]\nIf[SP]we[SP]can[SP]do[SP]that,[SP]no[SP]more[SP]rumors[SP]will\ncome[SP]true.",
    "nom_fr": "Jun",
    "texte_fr": "Il faut arrêter mon père.[1205][U+000F]\nSi on y arrive, plus aucune\nrumeur ne se réalisera."
  },
  {
    "id": 9,
    "offset": 279400,
    "data_size": 170,
    "slot_size": 174,
    "_term": [
      4358,
      4354,
      4355,
      5169
    ],
    "nom_orig": "Jun",
    "texte_orig": "The[SP]Maia[SP]Maiden...[1205][U+000F][SP]It[SP]seems[SP]my[SP]father[SP]still\nhopes[SP]to[SP]fulfill[SP]the[SP]Oracle...",
    "nom_fr": "Jun",
    "texte_fr": "La Vierge Maia...[1205][U+000F] Mon père\nespère toujours accomplir l'Oracle..."
  },
  {
    "id": 10,
    "offset": 279574,
    "data_size": 274,
    "slot_size": 278,
    "_term": [
      4358,
      4354,
      4355,
      5169
    ],
    "nom_orig": "Tamaki",
    "texte_orig": "The[SP]magazine[SP]sweepstakes[SP]rumor[SP]should[SP]come\ntrue[SP]now.[SP]I'll[SP]handle[SP]sending[SP]them[SP]in.[SP]You're\ntoo[SP]busy[SP]to[SP]do[SP]it[SP]yourselves,[SP]right?",
    "nom_fr": "Tamaki",
    "texte_fr": "La rumeur des concours devrait\nmarcher. Je vais les envoyer.\nVous êtes trop occupés, non ?"
  },
  {
    "id": 11,
    "offset": 279852,
    "data_size": 260,
    "slot_size": 264,
    "_term": [
      4361,
      4354,
      4355,
      5169
    ],
    "nom_orig": "Tamaki",
    "texte_orig": "Hello[SP]there![SP]What[SP]can[SP]I[SP]help[SP]you[SP]with?\n[1208][U+0004]Enter[SP]magazine[SP]sweepstakes\nTalk[SP]to[SP]Tamaki\nNothing\nLeave[SP]the[SP]detective[SP]agency",
    "nom_fr": "Tamaki",
    "texte_fr": "Hello there! What can I help you with?\n[1208][U+0004]Enter magazine sweepstakes\nTalk to Tamaki\nNothing\nLeave the detective agency",
    "question_orig": "Hello[SP]there![SP]What[SP]can[SP]I[SP]help[SP]you[SP]with?",
    "choix_orig": [
      "[U+0004]Enter[SP]magazine[SP]sweepstakes\nTalk[SP]to[SP]Tamaki\nNothing\nLeave[SP]the[SP]detective[SP]agency"
    ],
    "question_fr": "",
    "choix_fr": [
      ""
    ]
  },
  {
    "id": 12,
    "offset": 280116,
    "data_size": 234,
    "slot_size": 238,
    "_term": [
      4361,
      4354,
      4355,
      5169
    ],
    "nom_orig": "Tamaki",
    "texte_orig": "What[SP]can[SP]I[SP]help[SP]you[SP]with?\n[1208][U+0004]Enter[SP]magazine[SP]sweepstakes\nTalk[SP]to[SP]Tamaki\nNothing\nLeave[SP]the[SP]detective[SP]agency",
    "nom_fr": "Tamaki",
    "texte_fr": "What can I help you with?\n[1208][U+0004]Enter magazine sweepstakes\nTalk to Tamaki\nNothing\nLeave the detective agency",
    "question_orig": "What[SP]can[SP]I[SP]help[SP]you[SP]with?",
    "choix_orig": [
      "[U+0004]Enter[SP]magazine[SP]sweepstakes\nTalk[SP]to[SP]Tamaki\nNothing\nLeave[SP]the[SP]detective[SP]agency"
    ],
    "question_fr": "",
    "choix_fr": [
      ""
    ]
  },
  {
    "id": 13,
    "offset": 280354,
    "data_size": 192,
    "slot_size": 196,
    "_term": [
      4361,
      4354,
      4355,
      5169
    ],
    "nom_orig": "Tamaki",
    "texte_orig": "What[SP]do[SP]you[SP]want[SP]to[SP]talk[SP]about?\n[1208][U+0003]Make[SP]small[SP]talk\nAsk[SP]about[SP]the[SP]sweepstakes\nNothing",
    "nom_fr": "Tamaki",
    "texte_fr": "What do you want to talk about?\n[1208][U+0003]Make small talk\nAsk about the sweepstakes\nNothing",
    "question_orig": "What[SP]do[SP]you[SP]want[SP]to[SP]talk[SP]about?",
    "choix_orig": [
      "[U+0003]Make[SP]small[SP]talk\nAsk[SP]about[SP]the[SP]sweepstakes\nNothing"
    ],
    "question_fr": "",
    "choix_fr": [
      ""
    ]
  },
  {
    "id": 14,
    "offset": 280550,
    "data_size": 290,
    "slot_size": 294,
    "_term": [
      4358,
      4354,
      4355,
      5169
    ],
    "nom_orig": "Tamaki",
    "texte_orig": "Oh,[SP]did[SP]you[SP]check[SP]the[SP]ones[SP]you[SP]entered[SP]last\ntime?[SP]You[SP]get[SP]the[SP]prizes[SP]at[SP]Lisa-chan's[SP]house,\nso[SP]come[SP]back[SP]after[SP]you've[SP]seen[SP]if[SP]you[SP]won.",
    "nom_fr": "Tamaki",
    "texte_fr": "Avez-vous vérifié vos participations ?\nLes prix vont chez Lisa, revenez quand\nvous saurez si vous avez gagné."
  },
  {
    "id": 15,
    "offset": 280844,
    "data_size": 258,
    "slot_size": 262,
    "_term": [
      4358,
      4354,
      4355,
      5169
    ],
    "nom_orig": "Tamaki",
    "texte_orig": "Okay![1205][001E][SP]Wait...[SP]you[SP]don't[SP]have[SP]any[SP]magazines.\nThey[SP]sell[SP]them[SP]at[SP]Satomi[SP]Tadashi,[SP]so[SP]come\nback[SP]when[SP]you've[SP]bought[SP]some.",
    "nom_fr": "Tamaki",
    "texte_fr": "OK ![1205][001E] Attendez... pas de magazines.\nIls en vendent chez Satomi Tadashi.\nRevenez après en avoir acheté."
  },
  {
    "id": 16,
    "offset": 281106,
    "data_size": 234,
    "slot_size": 238,
    "_term": [
      4358,
      4354,
      4355,
      5169
    ],
    "nom_orig": "Tamaki",
    "texte_orig": "Okay![SP]Let's[SP]see...[SP]We're[SP]sending[SP]off[SP][120E][U+0001],\nright?[SP]I'll[SP]put[SP]down[SP]Lisa-chan's[SP]place[SP]as\nthe[SP]receiving[SP]address.",
    "nom_fr": "Tamaki",
    "texte_fr": "OK ! Voyons... On envoie [120E][U+0001] ?\nJe vais mettre l'adresse de Lisa\npour la livraison."
  },
  {
    "id": 17,
    "offset": 281344,
    "data_size": 86,
    "slot_size": 90,
    "_term": [
      4361,
      4354,
      4355,
      5169
    ],
    "nom_orig": "Tamaki",
    "texte_orig": "Are[SP]you[SP]sure?\n[1208][0002]Yes\nNever[SP]mind",
    "nom_fr": "Tamaki",
    "texte_fr": "Are you sure?\n[1208][0002]Yes\nNever mind",
    "question_orig": "Are[SP]you[SP]sure?",
    "choix_orig": [
      "Yes\nNever[SP]mind"
    ],
    "question_fr": "",
    "choix_fr": [
      ""
    ]
  },
  {
    "id": 18,
    "offset": 281434,
    "data_size": 156,
    "slot_size": 160,
    "_term": [
      4358,
      4354,
      4355,
      5169
    ],
    "nom_orig": "Tamaki",
    "texte_orig": "Gotcha![SP]I'll[SP]take[SP]care[SP]of[SP]sending[SP]them[SP]in.\nHope[SP]you[SP]win[SP]something!",
    "nom_fr": "Tamaki",
    "texte_fr": "Compris ! J'envoie ça. J'espère que\nvous gagnerez un truc !"
  },
  {
    "id": 19,
    "offset": 281594,
    "data_size": 162,
    "slot_size": 166,
    "_term": [
      4358,
      4354,
      4355,
      5169
    ],
    "nom_orig": "Tamaki",
    "texte_orig": "Gotcha![SP]Well,[SP]come[SP]back[SP]again[SP]when[SP]you[SP]want\nto[SP]enter[SP]the[SP]sweepstakes.",
    "nom_fr": "Tamaki",
    "texte_fr": "Compris ! Revenez quand vous\nvoudrez participer aux concours."
  },
  {
    "id": 20,
    "offset": 281760,
    "data_size": 256,
    "slot_size": 260,
    "_term": [
      4358,
      4354,
      4355,
      5169
    ],
    "nom_orig": "Tamaki",
    "texte_orig": "A[SP]sweepstakes[SP]is[SP]kind[SP]of[SP]like[SP]a[SP]raffle.[SP]You\nsend[SP]in[SP]magazines[SP]for[SP]chances[SP]to[SP]win[SP]a[SP]cool\nprize.[1121]It[SP]takes[SP]luck[SP]to[SP]win!",
    "nom_fr": "Tamaki",
    "texte_fr": "Un concours est une loterie. Envoyez\ndes magazines pour tenter de gagner\nun prix.[1121]Il faut de la chance !"
  },
  {
    "id": 21,
    "offset": 282020,
    "data_size": 286,
    "slot_size": 290,
    "_term": [
      4358,
      4354,
      4355,
      5169
    ],
    "nom_orig": "Tamaki",
    "texte_orig": "First[SP]buy[SP]Sweepstakes[SP]Magazines[SP]at[SP]Satomi\nTadashi,[SP]then[SP]bring[SP]them[SP]to[SP]me[SP]and[SP]I'll[SP]send\nthem[SP]in.[SP]Any[SP]prizes[SP]go[SP]to[SP]Lisa-chan's[SP]house.",
    "nom_fr": "Tamaki",
    "texte_fr": "Achetez des magazines de concours chez Satomi\nTadashi. Apportez-les-moi, je les envoie.\nLes prix iront chez Lisa."
  },
  {
    "id": 22,
    "offset": 282310,
    "data_size": 298,
    "slot_size": 302,
    "_term": [
      4358,
      4354,
      4355,
      5169
    ],
    "nom_orig": "Tamaki",
    "texte_orig": "There[SP]are[SP]a[SP]few[SP]rules![SP]You[SP]can[SP]only[SP]enter[SP]one\ncontest[SP]at[SP]a[SP]time.[SP]No[SP]more[SP]entries[SP]until[SP]the\nlast[SP]results[SP]are[SP]in.[SP]That's[SP]just[SP]how[SP]it[SP]works.",
    "nom_fr": "Tamaki",
    "texte_fr": "Un seul concours à la fois. Pas\nd'autre essai avant les résultats\ndu précédent. C'est comme ça."
  },
  {
    "id": 23,
    "offset": 282612,
    "data_size": 234,
    "slot_size": 238,
    "_term": [
      4358,
      4354,
      4355,
      5169
    ],
    "nom_orig": "Tamaki",
    "texte_orig": "Also,[SP]you[SP]can[SP]only[SP]send[SP]in[SP]99[SP]magazines[SP]per\nentry.[SP]The[SP]more[SP]you[SP]send,[SP]the[SP]better[SP]your\nchances[SP]of[SP]winning.",
    "nom_fr": "Tamaki",
    "texte_fr": "Limite de 99 magazines par envoi.\nPlus vous en envoyez, plus\nvous avez de chances de gagner."
  },
  {
    "id": 24,
    "offset": 282850,
    "data_size": 264,
    "slot_size": 268,
    "_term": [
      4358,
      4354,
      4355,
      5169
    ],
    "nom_orig": "Tamaki",
    "texte_orig": "Finally,[SP]it[SP]takes[SP]time[SP]for[SP]the[SP]results[SP]to\ncome[SP]in.[SP]You[SP]can't[SP]just[SP]sit[SP]around[SP]and[SP]wait.\nYou[SP]have[SP]to[SP]walk[SP]around[SP]dungeons.",
    "nom_fr": "Tamaki",
    "texte_fr": "Les résultats prennent du temps.\nN'attendez pas sans rien faire.\nExplorez des donjons."
  },
  {
    "id": 25,
    "offset": 283118,
    "data_size": 224,
    "slot_size": 228,
    "_term": [
      4358,
      4354,
      4355,
      5169
    ],
    "nom_orig": "Tamaki",
    "texte_orig": "The[SP]rest[SP]is[SP]up[SP]to[SP]persistence[SP]and[SP]luck!\nIf[SP]you[SP]keep[SP]at[SP]it,[SP]you[SP]might[SP]get[SP]yourself\nsome[SP]rare[SP]items...",
    "nom_fr": "Tamaki",
    "texte_fr": "Le reste dépend de la chance !\nSi vous insistez, vous pourriez\nobtenir des objets rares..."
  },
  {
    "id": 26,
    "offset": 283346,
    "data_size": 280,
    "slot_size": 284,
    "_term": [
      4358,
      4354,
      4355,
      5169
    ],
    "nom_orig": "Tamaki",
    "texte_orig": "I[SP]doubt[SP]there's[SP]a[SP]way[SP]to[SP]fix[SP]this[SP]by[SP]spreading\nrumors...[SP]Most[SP]people[SP]are[SP]thrilled[SP]with[SP]the\nstate[SP]of[SP]things.[SP]They'd[SP]never[SP]listen.",
    "nom_fr": "Tamaki",
    "texte_fr": "Répandre des rumeurs n'arrangera rien...\nLa plupart sont ravis de la situation.\nIls n'écouteraient pas."
  },
  {
    "id": 27,
    "offset": 283630,
    "data_size": 180,
    "slot_size": 184,
    "_term": [
      4358,
      4354,
      4355,
      5169
    ],
    "nom_orig": "Tamaki",
    "texte_orig": "I'm[SP]so[SP]sorry.[SP]We[SP]got[SP]careless.[1205][U+000F][SP]I[SP]hope[SP]you\ncan[SP]do[SP]something[SP]for[SP]that[SP]teacher.",
    "nom_fr": "Tamaki",
    "texte_fr": "Désolée. On a été négligents.[1205][U+000F]\nJ'espère que vous pourrez aider\nce prof."
  },
  {
    "id": 28,
    "offset": 283814,
    "data_size": 238,
    "slot_size": 242,
    "_term": [
      4358,
      4354,
      4355,
      5169
    ],
    "nom_orig": "Tamaki",
    "texte_orig": "I'll[SP]handle[SP]the[SP]scutwork[SP]of[SP]making\nsweepstakes[SP]entries,[SP]just[SP]as[SP]long[SP]as\nyou[SP]bring[SP]me[SP]Sweepstakes[SP]Magazines.",
    "nom_fr": "Tamaki",
    "texte_fr": "Je gère la paperasse pour les concours,\ntant que vous m'apportez des magazines."
  },
  {
    "id": 29,
    "offset": 284056,
    "data_size": 262,
    "slot_size": 266,
    "_term": [
      4358,
      4354,
      4355,
      5169
    ],
    "nom_orig": "Tadashi",
    "texte_orig": "It[SP]seems[SP]there[SP]are[SP]several[SP]theories[SP]on[SP]how[SP]the\nEarth[SP]will[SP]be[SP]destroyed[SP]going[SP]around...[1205][U+000F][SP]They're\npretty[SP]interesting...",
    "nom_fr": "Tadashi",
    "texte_fr": "Il y a plusieurs théories sur la\ndestruction de la Terre...[1205][U+000F]\nTrès intéressantes..."
  },
  {
    "id": 30,
    "offset": 284322,
    "data_size": 264,
    "slot_size": 268,
    "_term": [
      4358,
      4354,
      4355,
      5169
    ],
    "nom_orig": "Tadashi",
    "texte_orig": "Everyone[SP]agrees[SP]the[SP]Grand[SP]Cross[SP]will[SP]play[SP]a[SP]big\npart[SP]in[SP]the[SP]Earth's[SP]annihilation,[SP]but[SP]no[SP]one\ncan[SP]agree[SP]on[SP]how.[SP]Hmmmm...",
    "nom_fr": "Tadashi",
    "texte_fr": "Tous s'accordent sur le rôle de la Croix\nCosmique dans la fin du monde, mais personne\nne sait comment. Hmmmm..."
  },
  {
    "id": 31,
    "offset": 284590,
    "data_size": 304,
    "slot_size": 308,
    "_term": [
      4358,
      4354,
      4355,
      5169
    ],
    "nom_orig": "Tadashi",
    "texte_orig": "Hehehe![SP]I[SP]finally[SP]heard[SP]a[SP]convincing[SP]theory![1205][U+000F]\nAfter[SP]the[SP]Grand[SP]Cross,[SP]the[SP]balance[SP]of[SP]gravity\nwill[SP]be[SP]thrown[SP]off,[SP]stopping[SP]Earth's[SP]rotation.",
    "nom_fr": "Tadashi",
    "texte_fr": "Héhé ! Une théorie convaincante ![1205][U+000F]\nAprès la Croix, la gravité sera\ndéséquilibrée, arrêtant la rotation de la Terre."
  },
  {
    "id": 32,
    "offset": 284898,
    "data_size": 254,
    "slot_size": 258,
    "_term": [
      4358,
      4354,
      4355,
      5169
    ],
    "nom_orig": "Tadashi",
    "texte_orig": "There's[SP]a[SP]part[SP]in[SP]the[SP]In[SP]Lak'ech[SP]that[SP]hints[SP]at\nsomething[SP]like[SP]that,[SP]too.[1205][U+000F][SP]Looks[SP]like[SP]I've[SP]got\nit[SP]right[SP]this[SP]time.",
    "nom_fr": "Tadashi",
    "texte_fr": "In Lak'ech laisse aussi entendre un\ntruc du genre.[1205][U+000F] On dirait que j'ai vu\njuste cette fois."
  },
  {
    "id": 33,
    "offset": 285156,
    "data_size": 198,
    "slot_size": 202,
    "_term": [
      4358,
      4354,
      4355,
      5169
    ],
    "nom_orig": "Tadashi",
    "texte_orig": "I[SP]was[SP]here[SP]and[SP]I[SP]couldn't[SP]stop[SP]them[SP]from\nkidnapping[SP]the[SP]teacher...[1205][U+000F][SP]I'm[SP]so[SP]ashamed...",
    "nom_fr": "Tadashi",
    "texte_fr": "J'étais là et je n'ai pas pu empêcher\nl'enlèvement de la prof...[1205][U+000F] J'ai si honte..."
  },
  {
    "id": 34,
    "offset": 285358,
    "data_size": 276,
    "slot_size": 280,
    "_term": [
      4358,
      4354,
      4355,
      5169
    ],
    "nom_orig": "Tadashi",
    "texte_orig": "I[SP]guess[SP]I'm[SP]not[SP]cut[SP]out[SP]for[SP]this[SP]job...[1205][U+000F][SP]Should\nI[SP]apply[SP]to[SP]be[SP]a[SP]game[SP]designer[SP]instead?[1205][U+000F][SP]That\nsounds[SP]like[SP]it[SP]might[SP]be[SP]fun...",
    "nom_fr": "Tadashi",
    "texte_fr": "Je ne suis pas fait pour ce métier...[1205][U+000F]\nDevrais-je devenir game designer ?[1205][U+000F]\nÇa a l'air amusant..."
  },
  {
    "id": 35,
    "offset": 285638,
    "data_size": 208,
    "slot_size": 212,
    "_term": [
      4358,
      4354,
      4355,
      5169
    ],
    "nom_orig": "Tamaki",
    "texte_orig": "Pull[SP]yourself[SP]together,[SP]Tadashi![1205][U+000F][SP]You're[SP]lucky\nyou[SP]got[SP]a[SP]taste[SP]of[SP]the[SP]violence[SP]you[SP]admired.",
    "nom_fr": "Tamaki",
    "texte_fr": "Reprends-toi, Tadashi ![1205][U+000F] Tu as de la\nchance d'avoir goûté à la violence\nque tu admirais."
  },
  {
    "id": 36,
    "offset": 285850,
    "data_size": 72,
    "slot_size": 76,
    "_term": [
      4358,
      4354,
      4355,
      5169
    ],
    "nom_orig": "Tadashi",
    "texte_orig": "Yeah,[SP]but...[SP]it[SP]hurt...",
    "nom_fr": "Tadashi",
    "texte_fr": "Oui, mais... aïe..."
  },
  {
    "id": 37,
    "offset": 285926,
    "data_size": 318,
    "slot_size": 322,
    "_term": [
      4361,
      4354,
      4355,
      5169
    ],
    "nom_orig": "Chief[SP]Todoroki",
    "texte_orig": "You've[SP]come...[SP]What[SP]business[SP]do[SP]you[SP]have[SP]with\nus[SP]today?\n[1208][U+0005]Spread[SP]rumors\nCheck[SP]rumors\nTalk[SP]with[SP]the[SP]Chief\nCancel\nLeave[SP]the[SP]detective[SP]agency",
    "nom_fr": "Chef Todoroki",
    "texte_fr": "You've come... What business do you have with\nus today?\n[1208][U+0005]Spread rumors\nCheck rumors\nTalk with the Chief\nCancel\nLeave the detective agency",
    "question_orig": "You've[SP]come...[SP]What[SP]business[SP]do[SP]you[SP]have[SP]with\nus[SP]today?",
    "choix_orig": [
      "[U+0005]Spread[SP]rumors\nCheck[SP]rumors\nTalk[SP]with[SP]the[SP]Chief\nCancel\nLeave[SP]the[SP]detective[SP]agency"
    ],
    "question_fr": "",
    "choix_fr": [
      ""
    ]
  },
  {
    "id": 38,
    "offset": 286248,
    "data_size": 204,
    "slot_size": 208,
    "_term": [
      4361,
      4354,
      4355,
      5169
    ],
    "nom_orig": "Chief[SP]Todoroki",
    "texte_orig": "What's[SP]on[SP]your[SP]mind?\n[1208][U+0003]Make[SP]small[SP]talk\nAsk[SP]about[SP]rumors\n[1210][NULL]Non-displayed[SP]selection",
    "nom_fr": "Chef Todoroki",
    "texte_fr": "What's on your mind?\n[1208][U+0003]Make small talk\nAsk about rumors\n[1210][NULL]Non-displayed selection",
    "question_orig": "What's[SP]on[SP]your[SP]mind?",
    "choix_orig": [
      "[U+0003]Make[SP]small[SP]talk\nAsk[SP]about[SP]rumors\n[1210]Non-displayed[SP]selection"
    ],
    "question_fr": "",
    "choix_fr": [
      ""
    ]
  },
  {
    "id": 39,
    "offset": 286456,
    "data_size": 468,
    "slot_size": 472,
    "_term": [
      4361,
      4354,
      4355,
      5169
    ],
    "nom_orig": "Chief[SP]Todoroki",
    "texte_orig": "I'm[SP]sorry[SP]for[SP]what[SP]happened[SP]to[SP]that[SP]teacher.\nLooks[SP]like[SP]Tadashi[SP]took[SP]quite[SP]a[SP]beating...[1205][U+000F]\nSo,[SP]do[SP]you[SP]need[SP]me[SP]to[SP]spread[SP]any[SP]rumors?\n[1208][U+0005]Spread[SP]rumors\nCheck[SP]rumors\nTalk[SP]with[SP]the[SP]Chief\nCancel\nLeave[SP]the[SP]detective[SP]agency",
    "nom_fr": "Chef Todoroki",
    "texte_fr": "Désolé pour ce qui est arrivé à ce\nprof. On dirait que Tadashi a pris une\nraclée...[1205][U+000F] Une rumeur à répandre ?\n[1208][U+0005]Spread rumors\nCheck rumors\nTalk with the Chief\nCancel\nLeave the detective agency",
    "question_orig": "I'm[SP]sorry[SP]for[SP]what[SP]happened[SP]to[SP]that[SP]teacher.\nLooks[SP]like[SP]Tadashi[SP]took[SP]quite[SP]a[SP]beating...[1205][U+000F]\nSo,[SP]do[SP]you[SP]need[SP]me[SP]to[SP]spread[SP]any[SP]rumors?",
    "choix_orig": [
      "[U+0005]Spread[SP]rumors\nCheck[SP]rumors\nTalk[SP]with[SP]the[SP]Chief\nCancel\nLeave[SP]the[SP]detective[SP]agency"
    ],
    "question_fr": "",
    "choix_fr": [
      ""
    ]
  },
  {
    "id": 40,
    "offset": 286928,
    "data_size": 204,
    "slot_size": 208,
    "_term": [
      4361,
      4354,
      4355,
      5169
    ],
    "nom_orig": "Chief[SP]Todoroki",
    "texte_orig": "What's[SP]on[SP]your[SP]mind?\n[1208][U+0003]Make[SP]small[SP]talk\nAsk[SP]about[SP]rumors\n[1210][NULL]Non-displayed[SP]selection",
    "nom_fr": "Chef Todoroki",
    "texte_fr": "What's on your mind?\n[1208][U+0003]Make small talk\nAsk about rumors\n[1210][NULL]Non-displayed selection",
    "question_orig": "What's[SP]on[SP]your[SP]mind?",
    "choix_orig": [
      "[U+0003]Make[SP]small[SP]talk\nAsk[SP]about[SP]rumors\n[1210]Non-displayed[SP]selection"
    ],
    "question_fr": "",
    "choix_fr": [
      ""
    ]
  },
  {
    "id": 41,
    "offset": 287136,
    "data_size": 236,
    "slot_size": 240,
    "_term": [
      4361,
      4354,
      4355,
      5169
    ],
    "nom_orig": "Chief[SP]Todoroki",
    "texte_orig": "Anything[SP]else?\n[1208][U+0005]Spread[SP]rumors\nCheck[SP]rumors\nTalk[SP]with[SP]the[SP]Chief\nCancel\nLeave[SP]the[SP]detective[SP]agency",
    "nom_fr": "Chef Todoroki",
    "texte_fr": "Anything else?\n[1208][U+0005]Spread rumors\nCheck rumors\nTalk with the Chief\nCancel\nLeave the detective agency",
    "question_orig": "Anything[SP]else?",
    "choix_orig": [
      "[U+0005]Spread[SP]rumors\nCheck[SP]rumors\nTalk[SP]with[SP]the[SP]Chief\nCancel\nLeave[SP]the[SP]detective[SP]agency"
    ],
    "question_fr": "",
    "choix_fr": [
      ""
    ]
  },
  {
    "id": 42,
    "offset": 287376,
    "data_size": 204,
    "slot_size": 208,
    "_term": [
      4361,
      4354,
      4355,
      5169
    ],
    "nom_orig": "Chief[SP]Todoroki",
    "texte_orig": "What's[SP]on[SP]your[SP]mind?\n[1208][U+0003]Make[SP]small[SP]talk\nAsk[SP]about[SP]rumors\n[1210][NULL]Non-displayed[SP]selection",
    "nom_fr": "Chef Todoroki",
    "texte_fr": "What's on your mind?\n[1208][U+0003]Make small talk\nAsk about rumors\n[1210][NULL]Non-displayed selection",
    "question_orig": "What's[SP]on[SP]your[SP]mind?",
    "choix_orig": [
      "[U+0003]Make[SP]small[SP]talk\nAsk[SP]about[SP]rumors\n[1210]Non-displayed[SP]selection"
    ],
    "question_fr": "",
    "choix_fr": [
      ""
    ]
  },
  {
    "id": 43,
    "offset": 287584,
    "data_size": 264,
    "slot_size": 268,
    "_term": [
      4358,
      4354,
      4355,
      5169
    ],
    "nom_orig": "Chief[SP]Todoroki",
    "texte_orig": "As[SP]soon[SP]as[SP]they[SP]think[SP]they're[SP]saved,[SP]they[SP]begin\nspeculating[SP]on[SP]the[SP]end[SP]of[SP]the[SP]world...[1205][U+000F][SP]That's\nmankind[SP]for[SP]you.",
    "nom_fr": "Chef Todoroki",
    "texte_fr": "Dès qu'ils se croient sauvés, ils spéculent\nsur la fin du monde...[1205][U+000F] C'est l'humanité."
  },
  {
    "id": 44,
    "offset": 287852,
    "data_size": 212,
    "slot_size": 216,
    "_term": [
      4358,
      4354,
      4355,
      5169
    ],
    "nom_orig": "Chief[SP]Todoroki",
    "texte_orig": "It[SP]won't[SP]be[SP]any[SP]God[SP]or[SP]demon[SP]who[SP]brings[SP]about\nthat[SP]annihilation.[SP]It'll[SP]be[SP]man[SP]himself.",
    "nom_fr": "Chef Todoroki",
    "texte_fr": "Ce ne sera ni Dieu ni démon qui causera\ncette annihilation. Ce sera l'homme lui-même."
  },
  {
    "id": 45,
    "offset": 288068,
    "data_size": 258,
    "slot_size": 262,
    "_term": [
      4358,
      4354,
      4355,
      5169
    ],
    "nom_orig": "Chief[SP]Todoroki",
    "texte_orig": "In[SP]the[SP]end,[SP]maybe[SP]humanity[SP]deserves[SP]to[SP]be\nannihilated.[1205][U+000F][SP]Rumors[SP]are[SP]the[SP]hidden[SP]desires\nof[SP]mankind,[SP]after[SP]all.",
    "nom_fr": "Chef Todoroki",
    "texte_fr": "Peut-être que l'humanité mérite d'être\nanéantie.[1205][U+000F] Les rumeurs sont les\ndésirs cachés de l'homme."
  },
  {
    "id": 46,
    "offset": 288330,
    "data_size": 244,
    "slot_size": 248,
    "_term": [
      4358,
      4354,
      4355,
      5169
    ],
    "nom_orig": "Chief[SP]Todoroki",
    "texte_orig": "From[SP]that[SP]perspective,[SP]the[SP]state[SP]of[SP]things\nhere[SP]where[SP]rumors[SP]are[SP]becoming[SP]reality[SP]is\na[SP]genuine[SP]utopia.",
    "nom_fr": "Chef Todoroki",
    "texte_fr": "De ce point de vue, la situation\nici où les rumeurs deviennent\nréalité est une vraie utopie."
  },
  {
    "id": 47,
    "offset": 288578,
    "data_size": 308,
    "slot_size": 312,
    "_term": [
      4358,
      4354,
      4355,
      5169
    ],
    "nom_orig": "Chief[SP]Todoroki",
    "texte_orig": "But[SP]what[SP]about[SP]the[SP]bigger[SP]picture?[SP]The[SP]state[SP]of\nthe[SP]city[SP]and[SP]the[SP]Earth's[SP]future[SP]is[SP]every[SP]man's\nwish[SP]made[SP]manifest...[1205][U+000F][SP]It's[SP]our[SP]karma.",
    "nom_fr": "Chef Todoroki",
    "texte_fr": "Et dans l'ensemble ? La ville et l'avenir de la\nTerre sont le souhait de chaque homme\nrendu manifeste...[1205][U+000F] C'est notre karma."
  },
  {
    "id": 48,
    "offset": 288890,
    "data_size": 248,
    "slot_size": 252,
    "_term": [
      4358,
      4354,
      4355,
      5169
    ],
    "nom_orig": "Chief[SP]Todoroki",
    "texte_orig": "To[SP]think[SP]they'd[SP]strike[SP]when[SP]Tamaki[SP]and[SP]I[SP]were\nout...[1205][001E][SP]This[SP]was[SP]my[SP]mistake.[SP]I'm[SP]very[SP]sorry\nit[SP]happened.",
    "nom_fr": "Chef Todoroki",
    "texte_fr": "Ils ont frappé pendant notre\nabsence...[1205][001E] C'est mon erreur.\nJe suis vraiment désolé."
  },
  {
    "id": 49,
    "offset": 289142,
    "data_size": 298,
    "slot_size": 302,
    "_term": [
      4358,
      4354,
      4355,
      5169
    ],
    "nom_orig": "Chief[SP]Todoroki",
    "texte_orig": "But...[1205][U+000A][SP]I[SP]hope[SP]Tadashi[SP]understands[SP]now.[1205][U+000F][SP]This\nlife[SP]isn't[SP]as[SP]cool[SP]or[SP]clear-cut[SP]as[SP]they[SP]make\nit[SP]seem[SP]in[SP]TV[SP]shows[SP]and[SP]comic[SP]books.",
    "nom_fr": "Chef Todoroki",
    "texte_fr": "Mais...[1205][U+000A] J'espère que Tadashi a\ncompris.[1205][U+000F] La vie n'est pas aussi simple\net cool qu'à la télé ou dans les mangas."
  },
  {
    "id": 50,
    "offset": 289444,
    "data_size": 272,
    "slot_size": 276,
    "_term": [
      4358,
      4354,
      4355,
      5169
    ],
    "nom_orig": "Chief[SP]Todoroki",
    "texte_orig": "All[SP]we[SP]can[SP]do[SP]for[SP]you[SP]is[SP]to[SP]spread[SP]some\nrumors[SP]here[SP]and[SP]there.[SP]The[SP]rest[SP]is[SP]all[SP]up\nto[SP]you.[SP]Well[SP]then...[SP]Be[SP]seeing[SP]ya.",
    "nom_fr": "Chef Todoroki",
    "texte_fr": "On peut juste semer des rumeurs.\nLe reste dépend de vous. Bon...\nÀ plus."
  },
  {
    "id": 51,
    "offset": 289720,
    "data_size": 172,
    "slot_size": 176,
    "_term": [
      4358,
      4354,
      4355,
      5169
    ],
    "nom_orig": "Chief[SP]Todoroki",
    "texte_orig": "Sweepstakes,[SP]huh...?[SP]Talk[SP]to[SP]Tamaki-kun[SP]if\nyou[SP]want[SP]to[SP]enter[SP]them.",
    "nom_fr": "Chef Todoroki",
    "texte_fr": "Concours, hein... ? Parlez-en à\nTamaki pour y participer."
  },
  {
    "id": 52,
    "offset": 289896,
    "data_size": 192,
    "slot_size": 196,
    "_term": [
      4358,
      4354,
      4355,
      5169
    ],
    "nom_orig": "Lucky[SP]cat[SP]statue",
    "texte_orig": "100[SP]yen[SP]please,[SP]meow[1432][NULL][NULL][U+0007]\n100[SP]yen[SP]please,[SP]meow[1432][NULL][NULL][U+0007]\n100[SP]yen[SP]please,[SP]meow[1432][NULL][NULL][U+0007]",
    "nom_fr": "Statue de chat",
    "texte_fr": "100 yens stp, miaou[1432][NULL][NULL][U+0007]\n100 yens stp, miaou[1432][NULL][NULL][U+0007]\n100 yens stp, miaou[1432][NULL][NULL][U+0007]"
  },
  {
    "id": 53,
    "offset": 290092,
    "data_size": 172,
    "slot_size": 176,
    "_term": [
      4361,
      4354,
      4355,
      5169
    ],
    "nom_orig": "Lucky[SP]cat[SP]statue",
    "texte_orig": "100[SP]yen[SP]please,[SP]meow[1432][NULL][NULL][U+0007]\n[1208][0002]Put[SP]in[SP]100[SP]yen\nDon't[SP]put[SP]in[SP]anything",
    "nom_fr": "Statue de chat",
    "texte_fr": "100 yen please, meow[1432][NULL][NULL][U+0007]\n[1208][0002]Put in 100 yen\nDon't put in anything",
    "question_orig": "100[SP]yen[SP]please,[SP]meow[1432][NULL][NULL][U+0007]",
    "choix_orig": [
      "Put[SP]in[SP]100[SP]yen\nDon't[SP]put[SP]in[SP]anything"
    ],
    "question_fr": "",
    "choix_fr": [
      ""
    ]
  },
  {
    "id": 54,
    "offset": 290268,
    "data_size": 250,
    "slot_size": 254,
    "_term": [
      4358,
      4354,
      4355,
      5169
    ],
    "nom_orig": "Lucky[SP]cat[SP]statue",
    "texte_orig": "Oh,[SP]you're[SP]broke,[SP]meow[1432][NULL][NULL][U+0007]\nShow[SP]me[SP]a[SP]liar[SP]and[SP]I'll[SP]show[SP]you[SP]a[SP]thief,[SP]meow[1432][NULL][NULL][U+0007]\nGet[SP]out[SP]of[SP]here,[SP]hiss[1432][NULL][NULL][U+0007]",
    "nom_fr": "Statue de chat",
    "texte_fr": "T'es fauché, miaou[1432][NULL][NULL][U+0007]\nUn menteur est un voleur, miaou[1432][NULL][NULL][U+0007]\nVa-t'en d'ici, fsssh[1432][NULL][NULL][U+0007]"
  },
  {
    "id": 55,
    "offset": 290522,
    "data_size": 228,
    "slot_size": 232,
    "_term": [
      4358,
      4354,
      4355,
      5169
    ],
    "nom_orig": "Lucky[SP]cat[SP]statue",
    "texte_orig": "Purrrr...[SP]I'm[SP]touched[1432][NULL][NULL][U+0007][1205][U+000F]\nYou[SP]fed[SP]me[SP]20[SP]times,[SP]meow[1432][NULL][NULL][U+0007][1205][U+000F]\nI[SP]look[SP]forward[SP]to[SP]more,[SP]meow[1432][NULL][NULL][U+0007]",
    "nom_fr": "Statue de chat",
    "texte_fr": "Ronron... Touché[1432][NULL][NULL][U+0007][1205][U+000F]\nNourri 20 fois, miaou[1432][NULL][NULL][U+0007][1205][U+000F]\nJ'en attends encore, miaou[1432][NULL][NULL][U+0007]"
  },
  {
    "id": 56,
    "offset": 290754,
    "data_size": 244,
    "slot_size": 248,
    "_term": [
      4358,
      4354,
      4355,
      5169
    ],
    "nom_orig": "Lucky[SP]cat[SP]statue",
    "texte_orig": "Meowvelous![1432][NULL][NULL][U+0007][1205][U+000F]\nI[SP]can't[SP]believe[SP]you[SP]fed[SP]me[SP]50[SP]times,[SP]purrrr[1432][NULL][NULL][U+0007][1205][U+000F]\nYou're[SP]so[SP]generous,[SP]Misterrr[1432][NULL][NULL][U+0007]",
    "nom_fr": "Statue de chat",
    "texte_fr": "Miaourveilleux ![1432][NULL][NULL][U+0007][1205][U+000F]\nNourri 50 fois, ronron[1432][NULL][NULL][U+0007][1205][U+000F]\nTrès généreux, mooonsieur[1432][NULL][NULL][U+0007]"
  },
  {
    "id": 57,
    "offset": 291002,
    "data_size": 224,
    "slot_size": 228,
    "_term": [
      4358,
      4354,
      4355,
      5169
    ],
    "nom_orig": "Lucky[SP]cat[SP]statue",
    "texte_orig": "Amazing,[SP]meow![1205][U+000F]\nYou've[SP]fed[SP]me[SP]80[SP]times[SP]now,[SP]meow[1432][NULL][NULL][U+0007][1205][U+000F]\nDo[SP]you[SP]have[SP]a[SP]kitten[SP]agenda,[SP]meow?",
    "nom_fr": "Statue de chat",
    "texte_fr": "Superbe, miaou ![1205][U+000F]\nNourri 80 fois, miaou[1432][NULL][NULL][U+0007][1205][U+000F]\nAs-tu un plan caché, miaou ?"
  },
  {
    "id": 58,
    "offset": 291230,
    "data_size": 234,
    "slot_size": 238,
    "_term": [
      4358,
      4354,
      4355,
      5169
    ],
    "nom_orig": "Lucky[SP]cat[SP]statue",
    "texte_orig": "The[SP]time[SP]has[SP]finally[SP]come,[SP]meow...[1205][U+000F]\nAn[SP]even[SP]100[SP]feedings...[1205][U+000F]\nI've[SP]collected[SP]10,000[SP]yen,[SP]meow!",
    "nom_fr": "Statue de chat",
    "texte_fr": "L'heure est arrivée...[1205][U+000F]\nExactement 100 repas...[1205][U+000F]\nJ'ai récolté 10 000 yens, miaou !"
  },
  {
    "id": 59,
    "offset": 291468,
    "data_size": 190,
    "slot_size": 194,
    "_term": [
      4358,
      4354,
      5169
    ],
    "nom_orig": "Lucky[SP]cat[SP]statue",
    "texte_orig": "I[SP]feel[SP]bad[SP]at[SP]being[SP]given[SP]so[SP]much,[SP]meow![1205][U+000F]\nSo[SP]I[SP]have[SP]a[SP]purresent[SP]for[SP]you!",
    "nom_fr": "Statue de chat",
    "texte_fr": "I feel bad at being given so much, meow![1205][U+000F]\nSo I have a purresent for you!"
  },
  {
    "id": 60,
    "offset": 291662,
    "data_size": 134,
    "slot_size": 138,
    "_term": [
      4358,
      4354,
      4355,
      5169
    ],
    "nom_orig": "Lucky[SP]cat[SP]statue",
    "texte_orig": "Use[SP]this[SP][E4][NULL][NULL][U+0004]Incense[SP]Set[E4][NULL][NULL][0002][SP]wisely,[SP]meow[1432][NULL][NULL][U+0007]",
    "nom_fr": "Statue de chat",
    "texte_fr": "Utilise ce [E4][NULL][NULL][U+0004]Set d'Encens[E4][NULL][NULL][0002], miaou[1432][NULL][NULL][U+0007]"
  },
  {
    "id": 61,
    "offset": 291800,
    "data_size": 82,
    "slot_size": 86,
    "_term": [
      4358,
      4354,
      4355,
      5169
    ],
    "nom_orig": "Lucky[SP]cat[SP]statue",
    "texte_orig": "Thank[SP]you,[SP]meow[1432][NULL][NULL][U+0007]",
    "nom_fr": "Statue de chat",
    "texte_fr": "Merci, miaou[1432][NULL][NULL][U+0007]"
  },
  {
    "id": 62,
    "offset": 291886,
    "data_size": 76,
    "slot_size": 80,
    "_term": [
      4358,
      4354,
      4355,
      5169
    ],
    "nom_orig": "Lucky[SP]cat[SP]statue",
    "texte_orig": "...[1205][U+000F]Cheaps-cat!",
    "nom_fr": "Statue de chat",
    "texte_fr": "...[1205][U+000F]Radin !"
  },
  {
    "id": 63,
    "offset": 291966,
    "data_size": 174,
    "slot_size": 178,
    "_term": [
      4358,
      4354,
      4355,
      5169
    ],
    "nom_orig": "Lucky[SP]cat[SP]statue",
    "texte_orig": "That[SP]door[SP]doesn't[SP]open,[SP]meow[1432][NULL][NULL][U+0007]\nYou[SP]should[SP]stop[SP]trying,[SP]meow[1432][NULL][NULL][U+0007]",
    "nom_fr": "Statue de chat",
    "texte_fr": "La porte est fermée, miaou[1432][NULL][NULL][U+0007]\nInutile d'essayer, miaou[1432][NULL][NULL][U+0007]"
  },
  {
    "id": 64,
    "offset": 292144,
    "data_size": 244,
    "slot_size": 248,
    "_term": [
      4358,
      4354,
      4355,
      5169
    ],
    "nom_orig": "Ms.[SP]Ideal",
    "texte_orig": "Kashihara...[SP]The[SP]secrets[SP]of[SP]Xibalba[SP]you\nsealed[SP]away[SP]have[SP]become[SP]public[SP]knowledge...!\nWhat[SP]should[SP]I[SP]do...!?",
    "nom_fr": "Mme Idéale",
    "texte_fr": "Kashihara... Les secrets de Xibalba que\ntu as scellés sont devenus publics... !\nQue dois-je faire...!?"
  },
  {
    "id": 65,
    "offset": 292392,
    "data_size": 212,
    "slot_size": 216,
    "_term": [
      4361,
      4354,
      4355,
      5169
    ],
    "nom_orig": "Ms.[SP]Ideal",
    "texte_orig": "What[SP]should[SP]I[SP]do...!?\n[1208][U+0003]Ask[SP]about[SP]the[SP]In[SP]Lak'ech\nAsk[SP]about[SP]the[SP]Last[SP]Battalion\nLeave[SP]her[SP]be",
    "nom_fr": "Mme Idéale",
    "texte_fr": "Que dois-je faire...!?\n[1208][U+0003]L'In Lak'ech\nLe Bataillon\nLa laisser seule",
    "question_orig": "What[SP]should[SP]I[SP]do...!?",
    "choix_orig": [
      "[U+0003]Ask[SP]about[SP]the[SP]In[SP]Lak'ech\nAsk[SP]about[SP]the[SP]Last[SP]Battalion\nLeave[SP]her[SP]be"
    ],
    "question_fr": "",
    "choix_fr": [
      ""
    ]
  },
  {
    "id": 66,
    "offset": 292608,
    "data_size": 150,
    "slot_size": 154,
    "_term": [
      4358,
      4354,
      4355,
      5169
    ],
    "nom_orig": "Ms.[SP]Ideal",
    "texte_orig": "What[SP]is[SP]it!?[SP]What[SP]do[SP]you[SP]want[SP]to[SP]know[SP]about\nthe[SP]In[SP]Lak'ech?",
    "nom_fr": "Mme Idéale",
    "texte_fr": "Quoi !? Que voulez-vous savoir sur In Lak'ech ?"
  },
  {
    "id": 67,
    "offset": 292762,
    "data_size": 286,
    "slot_size": 290,
    "_term": [
      4361,
      4354,
      4355,
      5169
    ],
    "nom_orig": "Ms.[SP]Ideal",
    "texte_orig": "What[SP]do[SP]you[SP]want[SP]to[SP]know[SP]about[SP]the[SP]In[SP]Lak'ech?\n[1208][U+0005]About[SP]Kashihara\nAbout[SP]Sudou\nAbout[SP]its[SP]contents\nAbout[SP]Maians\nAbout[SP]Ideal[SP]Energy",
    "nom_fr": "Mme Idéale",
    "texte_fr": "Que voulez-vous savoir sur l'In Lak'ech?\n[1208][U+0005]Sur Kashihara\nSur Sudou\nLe contenu\nLes Maians\nL'Énergie Idéale",
    "question_orig": "What[SP]do[SP]you[SP]want[SP]to[SP]know[SP]about[SP]the[SP]In[SP]Lak'ech?",
    "choix_orig": [
      "[U+0005]About[SP]Kashihara\nAbout[SP]Sudou\nAbout[SP]its[SP]contents\nAbout[SP]Maians\nAbout[SP]Ideal[SP]Energy"
    ],
    "question_fr": "",
    "choix_fr": [
      ""
    ]
  },
  {
    "id": 68,
    "offset": 293052,
    "data_size": 296,
    "slot_size": 300,
    "_term": [
      4358,
      4354,
      4355,
      5169
    ],
    "nom_orig": "Ms.[SP]Ideal",
    "texte_orig": "He[SP]was[SP]a[SP]world[SP]history[SP]teacher[SP]at[SP]Sevens[SP]with\nme.[SP]He[SP]was[SP]always[SP]tormented[SP]that[SP]the[SP]history\nhe[SP]taught[SP]his[SP]students[SP]might[SP]be[SP]untrue...",
    "nom_fr": "Mme Idéale",
    "texte_fr": "Il enseignait l'histoire mondiale à Seven.\nIl était tourmenté à l'idée que l'histoire\nenseignée à ses élèves soit fausse..."
  },
  {
    "id": 69,
    "offset": 293352,
    "data_size": 214,
    "slot_size": 218,
    "_term": [
      4358,
      4354,
      4355,
      5169
    ],
    "nom_orig": "Ms.[SP]Ideal",
    "texte_orig": "He[SP]was[SP]a[SP]dreamer,[SP]who[SP]loved[SP]his[SP]students[SP]very\nmuch.[1205][001E][SP]Yet[SP]he[SP]died[SP]in[SP]such[SP]a[SP]dreadful[SP]way...",
    "nom_fr": "Mme Idéale",
    "texte_fr": "Un rêveur aimant ses élèves.[1205][001E] Pourtant,\nil est mort si atrocement..."
  },
  {
    "id": 70,
    "offset": 293570,
    "data_size": 196,
    "slot_size": 200,
    "_term": [
      4358,
      4354,
      4355,
      5169
    ],
    "nom_orig": "Ms.[SP]Ideal",
    "texte_orig": "Kashihara[SP]always[SP]felt[SP]as[SP]though[SP]he[SP]was[SP]being\nwatched[SP]while[SP]writing[SP]the[SP]In[SP]Lak'ech!",
    "nom_fr": "Mme Idéale",
    "texte_fr": "Kashihara se sentait toujours observé\nen écrivant In Lak'ech !"
  },
  {
    "id": 71,
    "offset": 293770,
    "data_size": 270,
    "slot_size": 274,
    "_term": [
      4358,
      4354,
      4355,
      5169
    ],
    "nom_orig": "Ms.[SP]Ideal",
    "texte_orig": "And[SP]then[SP]he[SP]was[SP]found[SP]dead,[SP]crushed[SP]between\nthe[SP]gears[SP]in[SP]the[SP]school's[SP]clock[SP]tower!\nThe[SP]Last[SP]Battalion[SP]killed[SP]Kashihara!",
    "nom_fr": "Mme Idéale",
    "texte_fr": "Puis on l'a trouvé mort, écrasé dans\nla tour de l'horloge !\nLe Bataillon l'a tué !"
  },
  {
    "id": 72,
    "offset": 294044,
    "data_size": 242,
    "slot_size": 246,
    "_term": [
      4358,
      4354,
      4355,
      5169
    ],
    "nom_orig": "Ms.[SP]Ideal",
    "texte_orig": "Sudou-kun[SP]was[SP]at[SP]Sevens[SP]too,[SP]as[SP]a[SP]student...[1205][001E]\nHe[SP]was[SP]a[SP]timid[SP]boy,[SP]afraid[SP]of[SP]his[SP]extremely\nstrict[SP]father.",
    "nom_fr": "Mme Idéale",
    "texte_fr": "Sudou était élève à Seven...[1205][001E] Un\ngarçon timide, effrayé par son père strict."
  },
  {
    "id": 73,
    "offset": 294290,
    "data_size": 282,
    "slot_size": 286,
    "_term": [
      4358,
      4354,
      4355,
      5169
    ],
    "nom_orig": "Ms.[SP]Ideal",
    "texte_orig": "He[SP]was[SP]a[SP]troublemaker[SP]who[SP]complained[SP]of\nhearing[SP]voices,[SP]and[SP]was[SP]rumored[SP]to[SP]be[SP]an\narsonist.[SP]But[SP]he[SP]was[SP]devoted[SP]to[SP]Kashihara...",
    "nom_fr": "Mme Idéale",
    "texte_fr": "Un fauteur de troubles entendant des voix.\nRumeur de pyromanie. Mais dévoué à\nKashihara..."
  },
  {
    "id": 74,
    "offset": 294576,
    "data_size": 246,
    "slot_size": 250,
    "_term": [
      4358,
      4354,
      4355,
      5169
    ],
    "nom_orig": "Ms.[SP]Ideal",
    "texte_orig": "It[SP]was[SP]Kashihara[SP]who[SP]noticed[SP]Sudou-kun's\ngift.[SP]He[SP]was[SP]a[SP]medium[SP]capable[SP]of[SP]hearing\nthe[SP]voices[SP]of[SP]the[SP]Maians.",
    "nom_fr": "Mme Idéale",
    "texte_fr": "Kashihara a vu son don. Sudou était un\nmédium entendant les Mayas."
  },
  {
    "id": 75,
    "offset": 294826,
    "data_size": 278,
    "slot_size": 282,
    "_term": [
      4358,
      4354,
      4355,
      5169
    ],
    "nom_orig": "Ms.[SP]Ideal",
    "texte_orig": "Slowly,[SP]Kashihara[SP]coaxed[SP]from[SP]him[SP]what\nbecame[SP]the[SP]Oracle[SP]of[SP]Maia.[SP]Sudou-kun[SP]was\nhappy[SP]to[SP]have[SP]someone[SP]who[SP]understood[SP]him...",
    "nom_fr": "Mme Idéale",
    "texte_fr": "Kashihara a tiré de lui l'Oracle de\nMaia. Sudou était heureux d'être compris..."
  },
  {
    "id": 76,
    "offset": 295108,
    "data_size": 234,
    "slot_size": 238,
    "_term": [
      4358,
      4354,
      4355,
      5169
    ],
    "nom_orig": "Ms.[SP]Ideal",
    "texte_orig": "Sudou-kun[SP]must[SP]have[SP]betrayed[SP]us[SP]and[SP]told[SP]the\nLast[SP]Battalion[SP]about[SP]Xibalba![SP]It's[SP]the[SP]only\nexplanation!",
    "nom_fr": "Mme Idéale",
    "texte_fr": "Sudou a dû nous trahir et parler de Xibalba\nau Bataillon ! Seule explication !"
  },
  {
    "id": 77,
    "offset": 295346,
    "data_size": 272,
    "slot_size": 276,
    "_term": [
      4358,
      4354,
      4355,
      5169
    ],
    "nom_orig": "Ms.[SP]Ideal",
    "texte_orig": "[1432][NULL][NULL][0014]In[SP]Lak'ech[1432][NULL][NULL][0014][SP]means[SP][1432][NULL][NULL][0014]you[SP]are[SP]another[SP]me[1432][NULL][NULL][0014][SP]in\nMayan.[1205][001E][SP]It's[SP]what[SP]we[SP]called[SP]the[SP]oracle[SP]that\nSudou-kun[SP]channeled.",
    "nom_fr": "Mme Idéale",
    "texte_fr": "[1432][NULL][NULL][0014]In Lak'ech[1432][NULL][NULL][0014] signifie [1432][NULL][NULL][0014]tu es un autre moi[1432][NULL][NULL][0014]\nen maya.[1205][001E] C'est le nom de l'oracle\nde Sudou."
  },
  {
    "id": 78,
    "offset": 295622,
    "data_size": 284,
    "slot_size": 288,
    "_term": [
      4358,
      4354,
      4355,
      5169
    ],
    "nom_orig": "Ms.[SP]Ideal",
    "texte_orig": "The[SP]Maians[SP]guided[SP]our[SP]evolution[SP]once,[SP]though\nthat[SP]stage[SP]is[SP]now[SP]lost.[1205][001E][SP]Our[SP]civilization[SP]as\nit[SP]stands[SP]is[SP]a[SP]remnant[SP]from[SP]then...",
    "nom_fr": "Mme Idéale",
    "texte_fr": "Les Mayas ont guidé notre évolution.[1205][001E]\nNotre civilisation n'est qu'un vestige..."
  },
  {
    "id": 79,
    "offset": 295910,
    "data_size": 248,
    "slot_size": 252,
    "_term": [
      4358,
      4354,
      4355,
      5169
    ],
    "nom_orig": "Ms.[SP]Ideal",
    "texte_orig": "The[SP]Bolontiku[SP]destroyed[SP]our[SP]ancestors[SP]and[SP]the\nOxlahuntiku.[SP]Their[SP]spaceship,[SP]Xibalba,[SP]lies\nunder[SP]this[SP]city...",
    "nom_fr": "Mme Idéale",
    "texte_fr": "Les Bolontiku ont détruit nos ancêtres\net les Oxlahuntiku. Xibalba est sous la ville..."
  },
  {
    "id": 80,
    "offset": 296162,
    "data_size": 282,
    "slot_size": 286,
    "_term": [
      4358,
      4354,
      4355,
      5169
    ],
    "nom_orig": "Ms.[SP]Ideal",
    "texte_orig": "Xibalba[SP]is[SP]the[SP]key[SP]to[SP]our[SP]evolution.[SP]We[SP]can't\nevolve[SP]without[SP]it...[1205][001E][SP]But[SP]it[SP]will[SP]come[SP]at[SP]the\ncost[SP]of[SP]this[SP]world's[SP]extinction!",
    "nom_fr": "Mme Idéale",
    "texte_fr": "Xibalba est la clé de notre évolution.[1205][001E]\nMais le prix est l'extinction du monde !"
  },
  {
    "id": 81,
    "offset": 296448,
    "data_size": 288,
    "slot_size": 292,
    "_term": [
      4358,
      4354,
      4355,
      5169
    ],
    "nom_orig": "Ms.[SP]Ideal",
    "texte_orig": "The[SP]Oracle[SP]promises[SP]the[SP]revival[SP]of[SP]Xibalba\nand[SP]an[SP]end[SP]to[SP]everything![SP]Kashihara[SP]sealed\nhis[SP]discovery[SP]for[SP]that[SP]reason,[SP]and[SP]yet...!",
    "nom_fr": "Mme Idéale",
    "texte_fr": "L'Oracle promet le retour de Xibalba et la\nfin de tout ! D'où le sceau de Kashihara !"
  },
  {
    "id": 82,
    "offset": 296740,
    "data_size": 260,
    "slot_size": 264,
    "_term": [
      4358,
      4354,
      4355,
      5169
    ],
    "nom_orig": "Ms.[SP]Ideal",
    "texte_orig": "The[SP]Maians[SP]came[SP]here[SP]from[SP]the[SP]Pleiades.\nThe[SP]two[SP]factions[SP]amongst[SP]them[SP]were[SP]in[SP]a\nperpetual[SP]state[SP]of[SP]galactic[SP]war...",
    "nom_fr": "Mme Idéale",
    "texte_fr": "Les Mayas venaient des Pléiades. Leurs\ndeux factions menaient une guerre\ngalactique..."
  },
  {
    "id": 83,
    "offset": 297004,
    "data_size": 274,
    "slot_size": 278,
    "_term": [
      4358,
      4354,
      4355,
      5169
    ],
    "nom_orig": "Ms.[SP]Ideal",
    "texte_orig": "The[SP]Mayans[SP]worshipped[SP]the[SP]Oxlahuntiku[SP]as[SP]gods\nof[SP]light...[1205][001E][SP]While[SP]they[SP]feared[SP]the[SP]Bolontiku\nas[SP]gods[SP]of[SP]the[SP]netherworld...",
    "nom_fr": "Mme Idéale",
    "texte_fr": "Ils vénéraient les Oxlahuntiku, dieux\nde lumière...[1205][001E] Et craignaient les\nBolontiku, dieux des enfers..."
  },
  {
    "id": 84,
    "offset": 297282,
    "data_size": 294,
    "slot_size": 298,
    "_term": [
      4358,
      4354,
      4355,
      5169
    ],
    "nom_orig": "Ms.[SP]Ideal",
    "texte_orig": "Their[SP]war[SP]consumed[SP]this[SP]solar[SP]system,[SP]and[SP]the\nOxlahuntiku[SP]perished...[1205][001E][SP]Those[SP]events[SP]are[SP]the\nsource[SP]of[SP]common[SP]legends[SP]of[SP]the[SP]flood.",
    "nom_fr": "Mme Idéale",
    "texte_fr": "La guerre a ravagé ce système, les\nOxlahuntiku ont péri...[1205][001E] C'est\nl'origine du mythe du déluge."
  },
  {
    "id": 85,
    "offset": 297580,
    "data_size": 230,
    "slot_size": 234,
    "_term": [
      4358,
      4354,
      4355,
      5169
    ],
    "nom_orig": "Ms.[SP]Ideal",
    "texte_orig": "But[SP]the[SP]victory[SP]took[SP]its[SP]toll[SP]on[SP]the\nBolontiku![SP]They[SP]ran[SP]out[SP]of[SP]power[SP]and[SP]were\nforced[SP]into[SP]slumber!",
    "nom_fr": "Mme Idéale",
    "texte_fr": "Mais cette victoire a coûté cher aux\nBolontiku ! Sans énergie, ils dorment !"
  },
  {
    "id": 86,
    "offset": 297814,
    "data_size": 252,
    "slot_size": 256,
    "_term": [
      4358,
      4354,
      4355,
      5169
    ],
    "nom_orig": "Ms.[SP]Ideal",
    "texte_orig": "To[SP]this[SP]day,[SP]they[SP]sleep[SP]below[SP]this[SP]city,\nabsorbing[SP]Ideal[SP]Energy[SP]and[SP]dreaming[SP]of[SP]the\nday[SP]when[SP]they[SP]will[SP]awaken!",
    "nom_fr": "Mme Idéale",
    "texte_fr": "Ils dorment sous cette ville, absorbant\nl'Énergie Idéale, rêvant de leur réveil !"
  },
  {
    "id": 87,
    "offset": 298070,
    "data_size": 266,
    "slot_size": 270,
    "_term": [
      4358,
      4354,
      4355,
      5169
    ],
    "nom_orig": "Ms.[SP]Ideal",
    "texte_orig": "Ideal[SP]Energy[SP]is[SP]the[SP]power[SP]of[SP]thought[SP]held[SP]by\nus[SP]living[SP]beings...[1205][001E][SP]It's[SP]a[SP]psychological\nenergy[SP]based[SP]on[SP]one's[SP]ideals.",
    "nom_fr": "Mme Idéale",
    "texte_fr": "L'Énergie Idéale est la force de nos pensées...[1205][001E]\nUne énergie psychique de nos idéaux."
  },
  {
    "id": 88,
    "offset": 298340,
    "data_size": 298,
    "slot_size": 302,
    "_term": [
      4358,
      4354,
      4355,
      5169
    ],
    "nom_orig": "Ms.[SP]Ideal",
    "texte_orig": "The[SP]energy[SP]is[SP]heightened[SP]most[SP]when[SP]one[SP]is\npassionate[SP]about[SP]one's[SP]ideals,[SP]or[SP]when[SP]one's\ndream[SP]comes[SP]true.[1205][001E][SP]It's[SP]fed[SP]by[SP]joie[SP]de[SP]vivre.",
    "nom_fr": "Mme Idéale",
    "texte_fr": "Elle croît quand on est passionné ou qu'un\nrêve se réalise.[1205][001E] Elle se nourrit de\njoie de vivre."
  },
  {
    "id": 89,
    "offset": 298642,
    "data_size": 282,
    "slot_size": 286,
    "_term": [
      4358,
      4354,
      4355,
      5169
    ],
    "nom_orig": "Ms.[SP]Ideal",
    "texte_orig": "Ideal[SP]Energy[SP]is[SP]the[SP]Maian[SP]source[SP]of[SP]power...[1205][001E]\nAnd[SP]the[SP]crystal[SP]skulls[SP]are[SP]OOPArts[SP]planted\nin[SP]mankind's[SP]history[SP]to[SP]collect[SP]it!",
    "nom_fr": "Mme Idéale",
    "texte_fr": "C'est la source d'énergie maya...[1205][001E] Et les\ncrânes sont des OOPArts plantés pour la récolter !"
  },
  {
    "id": 90,
    "offset": 298928,
    "data_size": 274,
    "slot_size": 278,
    "_term": [
      4358,
      4354,
      4355,
      5169
    ],
    "nom_orig": "Ms.[SP]Ideal",
    "texte_orig": "They're[SP]the[SP]keys[SP]to[SP]Xibalba[SP]and[SP]its[SP]power\nsource![SP]Whoever[SP]controls[SP]Xibalba[SP]and[SP]Ideal\nEnergy[SP]shall[SP]control[SP]mankind's[SP]fate!",
    "nom_fr": "Mme Idéale",
    "texte_fr": "Ce sont les clés de Xibalba ! Qui\nles contrôle dirigera l'humanité !"
  },
  {
    "id": 91,
    "offset": 299206,
    "data_size": 118,
    "slot_size": 122,
    "_term": [
      4358,
      4354,
      4355,
      5169
    ],
    "nom_orig": "Ms.[SP]Ideal",
    "texte_orig": "What!?[SP]What[SP]do[SP]you[SP]want[SP]to[SP]know[SP]about[SP]them?",
    "nom_fr": "Mme Idéale",
    "texte_fr": "Quoi !? Que voulez-vous savoir sur eux ?"
  },
  {
    "id": 92,
    "offset": 299328,
    "data_size": 196,
    "slot_size": 200,
    "_term": [
      4361,
      4354,
      4355,
      5169
    ],
    "nom_orig": "Ms.[SP]Ideal",
    "texte_orig": "What[SP]do[SP]you[SP]want[SP]to[SP]know[SP]about[SP]them?\n[1208][0002]About[SP]the[SP]Fuhrer\nAbout[SP]the[SP]Battalion[SP]itself",
    "nom_fr": "Mme Idéale",
    "texte_fr": "Que voulez-vous savoir?\n[1208][0002]Sur le Führer\nSur le Bataillon",
    "question_orig": "What[SP]do[SP]you[SP]want[SP]to[SP]know[SP]about[SP]them?",
    "choix_orig": [
      "About[SP]the[SP]Fuhrer\nAbout[SP]the[SP]Battalion[SP]itself"
    ],
    "question_fr": "",
    "choix_fr": [
      ""
    ]
  },
  {
    "id": 93,
    "offset": 299528,
    "data_size": 186,
    "slot_size": 190,
    "_term": [
      4358,
      4354,
      4355,
      5169
    ],
    "nom_orig": "Ms.[SP]Ideal",
    "texte_orig": "The[SP]greatest[SP]and[SP]worst[SP]dictator[SP]of[SP]the\ncentury![1205][001E][SP]You[SP]know[SP]that[SP]much,[SP]I[SP]hope.",
    "nom_fr": "Mme Idéale",
    "texte_fr": "Le plus grand et pire dictateur du\nsiècle ![1205][001E] J'espère que vous le savez."
  },
  {
    "id": 94,
    "offset": 299718,
    "data_size": 286,
    "slot_size": 290,
    "_term": [
      4358,
      4354,
      4355,
      5169
    ],
    "nom_orig": "Ms.[SP]Ideal",
    "texte_orig": "But[SP]do[SP]you[SP]know[SP]why[SP]he[SP]started[SP]a[SP]world[SP]war?\nHis[SP]true[SP]goal[SP]was[SP]to[SP]drive[SP]man[SP]to[SP]the[SP]brink\nof[SP]extinction[SP]and[SP]hasten[SP]our[SP]evolution!",
    "nom_fr": "Mme Idéale",
    "texte_fr": "Pourquoi une guerre mondiale ? Pour frôler\nl'extinction et hâter notre évolution !"
  },
  {
    "id": 95,
    "offset": 300008,
    "data_size": 300,
    "slot_size": 304,
    "_term": [
      4358,
      4354,
      4355,
      5169
    ],
    "nom_orig": "Ms.[SP]Ideal",
    "texte_orig": "He[SP]said[SP]so[SP]himself![1205][001E][SP]He's[SP]an[SP]immortal[SP]sorcerer\nwho[SP]learned[SP]magic[SP]from[SP]Mayan[SP]mystics.[SP]He\ncraved[SP]the[SP]secrets[SP]of[SP]ruins[SP]around[SP]the[SP]world!",
    "nom_fr": "Mme Idéale",
    "texte_fr": "Il l'a dit ![1205][001E] Sorcier immortel formé\npar les Mayas. Il convoitait les\nsecrets des ruines du monde !"
  },
  {
    "id": 96,
    "offset": 300312,
    "data_size": 268,
    "slot_size": 272,
    "_term": [
      4358,
      4354,
      4355,
      5169
    ],
    "nom_orig": "Ms.[SP]Ideal",
    "texte_orig": "You[SP]probably[SP]learned[SP]in[SP]school[SP]that[SP]he[SP]killed\nhimself,[SP]but[SP]he's[SP]very[SP]much[SP]alive![SP]There[SP]are\ncountless[SP]rumors[SP]saying[SP]so.",
    "nom_fr": "Mme Idéale",
    "texte_fr": "On dit qu'il s'est suicidé, mais il est\nvivant ! De nombreuses rumeurs\nl'affirment."
  },
  {
    "id": 97,
    "offset": 300584,
    "data_size": 260,
    "slot_size": 264,
    "_term": [
      4358,
      4354,
      4355,
      5169
    ],
    "nom_orig": "Ms.[SP]Ideal",
    "texte_orig": "And[SP]now[SP]he's[SP]figured[SP]out[SP]the[SP]secret[SP]behind\nXibalba![SP]He'll[SP]surely[SP]act[SP]on[SP]it[SP]to[SP]realize\nhis[SP]dream[SP]of[SP]becoming[SP]a[SP]god!",
    "nom_fr": "Mme Idéale",
    "texte_fr": "Et il a découvert le secret de Xibalba !\nIl va l'utiliser pour devenir un dieu !"
  },
  {
    "id": 98,
    "offset": 300848,
    "data_size": 298,
    "slot_size": 302,
    "_term": [
      4358,
      4354,
      4355,
      5169
    ],
    "nom_orig": "Ms.[SP]Ideal",
    "texte_orig": "The[SP]Last[SP]Battalion[SP]lurks[SP]in[SP]a[SP]secret[SP]base\nsomewhere[SP]in[SP]the[SP]South[SP]Pole[SP]or[SP]South[SP]America,\nwhere[SP]they[SP]plot[SP]to[SP]fulfill[SP]the[SP]Fuhrer's[SP]goal!",
    "nom_fr": "Mme Idéale",
    "texte_fr": "Le Bataillon se cache au pôle Sud ou en\nAmérique du Sud, préparant le\nplan du Führer !"
  },
  {
    "id": 99,
    "offset": 301150,
    "data_size": 232,
    "slot_size": 236,
    "_term": [
      4358,
      4354,
      4355,
      5169
    ],
    "nom_orig": "Ms.[SP]Ideal",
    "texte_orig": "They[SP]have[SP]cutting-edge[SP]weaponry[SP]and\nsuperhuman[SP]units[SP]ready[SP]and[SP]waiting[SP]for\nthe[SP]right[SP]time[SP]to[SP]strike!",
    "nom_fr": "Mme Idéale",
    "texte_fr": "Ils ont des armes de pointe et des\nunités surhumaines prêtes à frapper !"
  },
  {
    "id": 100,
    "offset": 301386,
    "data_size": 262,
    "slot_size": 266,
    "_term": [
      4358,
      4354,
      4355,
      5169
    ],
    "nom_orig": "Ms.[SP]Ideal",
    "texte_orig": "The[SP]most[SP]fearsome[SP]of[SP]them[SP]are[SP]the[SP]core[SP]of\nthe[SP]Last[SP]Battalion...[SP]A[SP]secret[SP]unit[SP]called\nthe[SP]Order[SP]of[SP]the[SP]Holy[SP]Lance...",
    "nom_fr": "Mme Idéale",
    "texte_fr": "Le cœur du Bataillon... L'Ordre de\nla Sainte Lance..."
  },
  {
    "id": 101,
    "offset": 301652,
    "data_size": 242,
    "slot_size": 246,
    "_term": [
      4358,
      4354,
      4355,
      5169
    ],
    "nom_orig": "Ms.[SP]Ideal",
    "texte_orig": "This[SP]Order[SP]of[SP]the[SP]Holy[SP]Lance[SP]has[SP]supposedly\ndiscovered[SP]the[SP]Spear[SP]of[SP]Destiny,[SP]a[SP]relic[SP]of\nChrist's[SP]miracle!",
    "nom_fr": "Mme Idéale",
    "texte_fr": "L'Ordre de la Sainte Lance aurait découvert la\nLance du Destin, relique du miracle du Christ !"
  },
  {
    "id": 102,
    "offset": 301898,
    "data_size": 228,
    "slot_size": 232,
    "_term": [
      4358,
      4354,
      4355,
      5169
    ],
    "nom_orig": "Ms.[SP]Ideal",
    "texte_orig": "It[SP]is[SP]said[SP]that[SP]whoever[SP]possesses[SP]the[SP]Spear\nof[SP]Destiny[SP]will[SP]rule[SP]the[SP]world...[SP]You[SP]must\nbe[SP]careful!",
    "nom_fr": "Mme Idéale",
    "texte_fr": "On dit que celui qui possède la Lance\ndominera le monde... Prudence !"
  },
  {
    "id": 103,
    "offset": 313066,
    "data_size": 94,
    "slot_size": 98,
    "_term": [
      4358,
      4354,
      5169
    ],
    "nom_orig": "Chief[SP]Todoroki",
    "texte_orig": "Want[SP]the[SP]lowdown[SP]on[SP]rumors?",
    "nom_fr": "Chef Todoroki",
    "texte_fr": "Les rumeurs t'intéressent?"
  },
  {
    "id": 104,
    "offset": 313164,
    "data_size": 198,
    "slot_size": 202,
    "_term": [
      4358,
      4354,
      5169
    ],
    "nom_orig": "Chief[SP]Todoroki",
    "texte_orig": "Ask[SP]me[SP]to[SP]spread[SP]a[SP]rumor[SP]of[SP]your[SP]choice[SP]and\nI'll[SP]do[SP]it.[SP]Not[SP]for[SP]free,[SP]mind[SP]you.",
    "nom_fr": "Chef Todoroki",
    "texte_fr": "Demande-moi de répandre une rumeur et\nje le ferai. Mais pas gratuitement."
  },
  {
    "id": 105,
    "offset": 313366,
    "data_size": 156,
    "slot_size": 160,
    "_term": [
      4358,
      4354,
      5169
    ],
    "nom_orig": "Chief[SP]Todoroki",
    "texte_orig": "You'll[SP]need[SP]to[SP]bring[SP]me[SP]rumors[SP]you[SP]hear[SP]from\nrumormongers.",
    "nom_fr": "Chef Todoroki",
    "texte_fr": "Apporte-moi les rumeurs que tu\nentends des colporteurs."
  },
  {
    "id": 106,
    "offset": 313526,
    "data_size": 200,
    "slot_size": 204,
    "_term": [
      4358,
      4354,
      5169
    ],
    "nom_orig": "Chief[SP]Todoroki",
    "texte_orig": "There[SP]are[SP]rumormongers[SP]everywhere[SP]in[SP]Sumaru.\nDig[SP]a[SP]little,[SP]and[SP]you'll[SP]find[SP]them.",
    "nom_fr": "Chef Todoroki",
    "texte_fr": "Il y a des colporteurs partout dans\nSumaru. Cherche, tu les trouveras."
  },
  {
    "id": 107,
    "offset": 313730,
    "data_size": 220,
    "slot_size": 224,
    "_term": [
      4358,
      4354,
      5169
    ],
    "nom_orig": "Chief[SP]Todoroki",
    "texte_orig": "You[SP]can[SP]remind[SP]yourself[SP]which[SP]rumors[SP]are\nalready[SP]circulating[SP]by[SP]asking[SP]me[SP]to[SP]check\nrumors.",
    "nom_fr": "Chef Todoroki",
    "texte_fr": "Tu peux te rappeler des rumeurs déjà\nen circulation en me demandant de\nles vérifier."
  },
  {
    "id": 108,
    "offset": 313954,
    "data_size": 280,
    "slot_size": 284,
    "_term": [
      4358,
      4354,
      4355,
      5169
    ],
    "nom_orig": "Chief[SP]Todoroki",
    "texte_orig": "Not[SP]only[SP]can[SP]you[SP]remember[SP]which[SP]rumors[SP]I've\nbeen[SP]putting[SP]out[SP]there[SP]for[SP]you,[SP]you[SP]can[SP]see\nwhich[SP]ones[SP]demons[SP]are[SP]spreading.",
    "nom_fr": "Chef Todoroki",
    "texte_fr": "Non seulement tu peux voir celles que\nj'ai diffusées, mais aussi celles\nque les démons répandent."
  },
  {
    "id": 109,
    "offset": 314238,
    "data_size": 182,
    "slot_size": 186,
    "_term": [
      4361,
      4354,
      4355,
      5169
    ],
    "nom_orig": "Chief[SP]Todoroki",
    "texte_orig": "I'll[SP]spread[SP]that[SP]rumor[SP]for[SP]you[SP]gratis.\nIt's[SP]the[SP]one[SP]you[SP]want?\n[1208][0002]Yes\nNo",
    "nom_fr": "Chef Todoroki",
    "texte_fr": "Je répands cette rumeur gratis.\nC'est bien celle-là ?\n[1208][0002]Oui\nNon",
    "question_orig": "I'll[SP]spread[SP]that[SP]rumor[SP]for[SP]you[SP]gratis.\nIt's[SP]the[SP]one[SP]you[SP]want?",
    "choix_orig": [
      "Yes\nNo"
    ],
    "question_fr": "",
    "choix_fr": [
      ""
    ]
  },
  {
    "id": 110,
    "offset": 314424,
    "data_size": 206,
    "slot_size": 210,
    "_term": [
      4361,
      4354,
      4355,
      5169
    ],
    "nom_orig": "Chief[SP]Todoroki",
    "texte_orig": "Spreading[SP]that[SP]rumor[SP]will[SP]cost[SP]you[SP]3,000[SP]yen.\nYou[SP]still[SP]want[SP]me[SP]to[SP]do[SP]it?\n[1208][0002]Yes\nNo",
    "nom_fr": "Chef Todoroki",
    "texte_fr": "Répandre cette rumeur coûte 3000 yens.\nToujours partant ?\n[1208][0002]Oui\nNon",
    "question_orig": "Spreading[SP]that[SP]rumor[SP]will[SP]cost[SP]you[SP]3,000[SP]yen.\nYou[SP]still[SP]want[SP]me[SP]to[SP]do[SP]it?",
    "choix_orig": [
      "Yes\nNo"
    ],
    "question_fr": "",
    "choix_fr": [
      ""
    ]
  }
]
