[
    {
        "id": 0,
        "offset": 247542,
        "data_size": 284,
        "slot_size": 288,
        "_term": [
            4358,
            4354,
            4355,
            5169
        ],
        "nom_orig": "Ginji-sounding[SP]man",
        "texte_orig": "Ahaha...[SP]My[SP]darling[SP]butterflies...[1205][001E][SP]The[SP]energy\nfrom[SP]your[SP]ideals[SP]will[SP]bring[SP]fruition[SP]to[SP]the\nMasked[SP]Circle's[SP]dreams...",
        "nom_fr": "Voix de Ginji",
        "texte_fr": "Ahaha... Mes jolis papillons...[1205][001E]\nL'énergie de vos idéaux va concrétiser\nles rêves du Cercle Masqué..."
    },
    {
        "id": 1,
        "offset": 247830,
        "data_size": 234,
        "slot_size": 238,
        "_term": [
            4358,
            4354,
            4355,
            5169
        ],
        "nom_orig": "Ginji-sounding[SP]man",
        "texte_orig": "Flutter[SP]even[SP]harder[SP]now...[SP]Higher...\nand[SP]further...[1205][001E][SP]Don't[SP]let[SP]those[SP]dreams\nbe[SP]exhausted...",
        "nom_fr": "Voix de Ginji",
        "texte_fr": "Voletez encore plus fort... Plus\nhaut... et plus loin...[1205][001E] Ne laissez\npas ces rêves s'épuiser..."
    },
    {
        "id": 2,
        "offset": 248068,
        "data_size": 312,
        "slot_size": 316,
        "_term": [
            4358,
            4354,
            4355,
            5169
        ],
        "nom_orig": "Mami[1121]&[SP]Miho",
        "texte_orig": "Glory[SP]to[SP]the[SP]Mask...\n[E1][E2]\n[E3][E4][NULL][NULL]\"Prince[SP]Taurus\nI,[SP]Ginji[SP]Sasaki...[1205][001E][SP]rather,[SP]Prince[SP]Taurus,\nwould[SP]like[SP]to[SP]introduce[SP]a[SP]new[SP]member[SP]to\nyour[SP]group.",
        "nom_fr": "Mami[1121]& Miho",
        "texte_fr": "Gloire au Masque... [E1][E2] [E3][E4][NULL][NULL]\"Prince Taureau[1205][U+000F]\nGinji Sasaki...[1205][001E] ou plutôt Prince Taureau,\nvous présente un nouveau membre."
    },
    {
        "id": 3,
        "offset": 248384,
        "data_size": 114,
        "slot_size": 118,
        "_term": [
            4358,
            4354,
            4355,
            5169
        ],
        "nom_orig": "Prince[SP]Taurus",
        "texte_orig": "Now,[SP]Lisa-kun...[1205][001E][SP]Call[SP]Master[SP]Joker.",
        "nom_fr": "Prince Taureau",
        "texte_fr": "Lisa...[1205][001E] Appelle Maître Joker."
    },
    {
        "id": 4,
        "offset": 248502,
        "data_size": 108,
        "slot_size": 112,
        "_term": [
            4358,
            4354,
            4355,
            5169
        ],
        "nom_orig": "Mami",
        "texte_orig": "Lisa...[1205][001E][SP]Let's[SP]take[SP]flight[SP]together,[SP]okay?",
        "nom_fr": "Mami",
        "texte_fr": "Lisa...[1205][001E] On s'envole ensemble, ok?"
    },
    {
        "id": 5,
        "offset": 248614,
        "data_size": 136,
        "slot_size": 140,
        "_term": [
            4358,
            4354,
            4355,
            5169
        ],
        "nom_orig": "Miho",
        "texte_orig": "The[SP]three[SP]of[SP]us[SP]promised[SP]to[SP]become[SP]idols\ntogether,[SP]right?",
        "nom_fr": "Miho",
        "texte_fr": "On a promis de devenir idoles\ntoutes les trois, non?"
    },
    {
        "id": 6,
        "offset": 248754,
        "data_size": 48,
        "slot_size": 52,
        "_term": [
            4358,
            4354,
            4355,
            5169
        ],
        "nom_orig": "Ginko",
        "texte_orig": "Promised...?",
        "nom_fr": "Ginko",
        "texte_fr": "Promis...?"
    },
    {
        "id": 7,
        "offset": 248806,
        "data_size": 58,
        "slot_size": 62,
        "_term": [
            4358,
            4354,
            4355,
            5169
        ],
        "nom_orig": "Ginko",
        "texte_orig": "Where...[SP]are[SP]you?",
        "nom_fr": "Ginko",
        "texte_fr": "Où... êtes-vous?"
    },
    {
        "id": 8,
        "offset": 248868,
        "data_size": 238,
        "slot_size": 242,
        "_term": [
            4358,
            4354,
            4355,
            5169
        ],
        "nom_orig": "Ginko",
        "texte_orig": "I'm[SP]sorry,[SP]Sheba,[SP]Mee-ho...[SP]I'm[SP]really[SP]glad\nto[SP]know[SP]how[SP]you[SP]two[SP]felt[SP]about[SP]me...[1205][001E][SP]But[SP]I\ncan't[SP]go[SP]with[SP]you.",
        "nom_fr": "Ginko",
        "texte_fr": "Désolée, Sheba, Mee-ho... Je suis\ncontente de savoir ce que vous\nressentez...[1205][001E] Mais je viens pas."
    },
    {
        "id": 9,
        "offset": 249110,
        "data_size": 250,
        "slot_size": 254,
        "_term": [
            4358,
            4354,
            4355,
            5169
        ],
        "nom_orig": "Ginko",
        "texte_orig": "[1113][SP]and[SP]the[SP]others[SP]are[SP]my[SP]friends[SP]too...\nI[SP]can't[SP]betray[SP]them![1205][001E][SP]Plus...[SP]I[SP]can't[SP]be[SP]happy\nliving[SP]a[SP]secondhand[SP]dream!",
        "nom_fr": "Ginko",
        "texte_fr": "[1113]et les autres sont aussi mes\namis... Je peux pas les trahir![1205][001E] Et je\nrefuse de vivre un rêve d'emprunt!"
    },
    {
        "id": 10,
        "offset": 249364,
        "data_size": 222,
        "slot_size": 226,
        "_term": [
            4358,
            4354,
            4355,
            5169
        ],
        "nom_orig": "Ginko",
        "texte_orig": "Maya-san[SP]and[SP]the[SP]others[SP]will[SP]be[SP]here\nsoon![SP]You[SP]don't[SP]have[SP]to[SP]stay![SP]We[SP]can[SP]get\nout[SP]of[SP]here[SP]together!",
        "nom_fr": "Ginko",
        "texte_fr": "Maya-san et les autres arrivent! Vous n'avez\npas à rester! On peut sortir d'ici ensemble!"
    }
]